pyaftership/__init__.py
pyaftership/aftership.py
pyaftership/base.py
pyaftership/const.py
pyaftership/couriers.py
pyaftership/exceptions.py
pyaftership/trackings.py
pyaftership-23.1.0.dist-info/LICENCE.md
pyaftership-23.1.0.dist-info/METADATA
pyaftership-23.1.0.dist-info/WHEEL
pyaftership-23.1.0.dist-info/top_level.txt
pyaftership-23.1.0.dist-info/RECORD
