Metadata-Version: 2.1
Name: pyaftership
Version: 23.1.0
Summary: Async Python wrapper for the AfterShip API.
Home-page: https://github.com/ludeeus/pyaftership
Author: Ludeeus
Author-email: hi@ludeeus.dev
License: MIT license
Classifier: Intended Audience :: Developers
Classifier: License :: OSI Approved :: MIT License
Classifier: Natural Language :: English
Classifier: Programming Language :: Python :: 3
Classifier: Programming Language :: Python :: 3.7
Classifier: Programming Language :: Python :: 3.8
Classifier: Programming Language :: Python :: 3.9
Classifier: Topic :: Software Development :: Libraries :: Python Modules
License-File: LICENCE.md
Requires-Dist: aiohttp (<4.0,>=3.6.1)
